__init__.py
bencode_reader.py
edn.py
patch_registry.py
pod_modules.py
python_pods.py
resolver.py
transit2.py
python_pods-0.1.0.dist-info/METADATA
python_pods-0.1.0.dist-info/WHEEL
python_pods-0.1.0.dist-info/top_level.txt
python_pods-0.1.0.dist-info/RECORD
