Metadata-Version: 2.4
Name: python-pods
Version: 0.1.0
Summary: A faithful port of babashka pods to python
License: MIT
Project-URL: Homepage, https://github.com/judepayne/python-pods
Requires-Python: >=3.13
Requires-Dist: bencode-py>=4.0.0
Requires-Dist: edn-format>=0.7.5
Requires-Dist: pytest>=8.4.0
Requires-Dist: requests>=2.32.3
Requires-Dist: tomli>=2.2.1
Requires-Dist: transit-python2>=0.8.321
